TS_PCA/__init__.py
TS_PCA/barycenter.py
TS_PCA/classifier.py
TS_PCA/kernel.py
TS_PCA/lddmm.py
TS_PCA/loss.py
TS_PCA/optimizer.py
TS_PCA/optimizer_new_memory_not_use.py
TS_PCA/plotting.py
TS_PCA/statistic.py
TS_PCA/utils.py
ts_pca-0.0.2.dist-info/licenses/LICENSE
ts_pca-0.0.2.dist-info/METADATA
ts_pca-0.0.2.dist-info/WHEEL
ts_pca-0.0.2.dist-info/top_level.txt
ts_pca-0.0.2.dist-info/RECORD
