Metadata-Version: 2.4
Name: TS-PCA
Version: 0.0.2
Summary: A package for unsupervised representation and principal component analysis of irregularly sampled time series with variable size relying on the shape analysis literature.
Author-email: Samuel Gruffaz <samuel.gruffaz@ens-paris-saclay.fr>, Thibaut Germain <thibaut.germain@ens-paris-saclay.fr>
Maintainer-email: Samuel Gruffaz <samuel.gruffaz@ens-paris-saclay.fr>, Thibaut Germain <thibaut.germain@ens-paris-saclay.fr>
License: Creative Commons Legal Code
Project-URL: Repository, https://github.com/samuelgruffaz/PCA_for_time_series.git
License-File: LICENSE
Requires-Dist: jax>=0.4.30
Requires-Dist: optax>=0.2.3
Requires-Dist: matplotlib>=3.9.1
Requires-Dist: numpy>=2.0.2
Requires-Dist: scipy>=1.13.1
Requires-Dist: pandas>=2.2.2
Requires-Dist: scikit-learn>=1.5.1
Dynamic: license-file
